<?xml version="1.0" encoding="UTF-8"?>
<song>
  <title>Joyful, Joyful, We Adore Thee</title>
  <author></author>
  <copyright></copyright>
  <hymn_number>SHL 009</hymn_number>
  <presentation></presentation>
  <ccli></ccli>
  <capo print="false"></capo>
  <key></key>
  <aka></aka>
  <key_line></key_line>
  <user1></user1>
  <user2></user2>
  <user3></user3>
  <theme></theme>
  <tempo></tempo>
  <time_sig></time_sig>
  <lyrics>[v1]
 1) Joyful, joyful, we adore Thee,
 God of glory, Lord of love;
 Hearts unfold like flow’rs before Thee,
 Opening to the sun above.
 Melt the clouds of sin and sadness;
 Drive the dark of doubt away.
 Giver of immortal gladness,
 Fill us with the light of day.
[v2]
 2) All Thy works with joy surround Thee,
 Earth and heav’n reflect Thy rays.
 Stars and angels sing around Thee,
 Center of unbroken praise.
 Field and forest, vale and mountain,
 Flowery meadow, flashing sea,
 Chanting bird and flowing fountain
 Call us to rejoice in Thee!
[v3]
 3) Thou art giving and forgiving,
 Ever blessing, ever blest,
 Wellspring of the joy of living,
 Ocean depth of happy rest!
 Thou our Father, Christ our Brother—
 All who live in love are Thine.
 Teach us how to love each other;
 Lift us to the joy divine!
[v4]
 4) Mortals, join the mighty chorus
 Which the morning stars began;
 Love divine is reigning o’er us,
 Leading us with mercy’s hand.
 Ever singing, march we onward,
 Victors in the midst of strife.
 Joyful music leads us Sunward
 In the triumph song of life!
[E]
 1) Joyful, joyful, we adore Thee,
 God of glory, Lord of love;
 Hearts unfold like flow’rs before Thee,
 Opening to the sun above.
 Melt the clouds of sin and sadness;
 Drive the dark of doubt away.
 Giver of immortal gladness,
 Fill us with the light of day.
 2) All Thy works with joy surround Thee,
 Earth and heav’n reflect Thy rays.
 Stars and angels sing around Thee,
 Center of unbroken praise.
 Field and forest, vale and mountain,
 Flowery meadow, flashing sea,
 Chanting bird and flowing fountain
 Call us to rejoice in Thee!
 3) Thou art giving and forgiving,
 Ever blessing, ever blest,
 Wellspring of the joy of living,
 Ocean depth of happy rest!
 Thou our Father, Christ our Brother—
 All who live in love are Thine.
 Teach us how to love each other;
 Lift us to the joy divine!
 4) Mortals, join the mighty chorus
 Which the morning stars began;
 Love divine is reigning o’er us,
 Leading us with mercy’s hand.
 Ever singing, march we onward,
 Victors in the midst of strife.
 Joyful music leads us Sunward
 In the triumph song of life!</lyrics></song>