<?xml version="1.0" encoding="UTF-8"?>
<song>
  <title>叩叩磐石发出活水</title>
  <lyrics>[V1]
 在旷野加低斯，以色列百姓，因干渴快要死，神就发命令：
 吩咐磐石发出活水来！击打勿再施，因早已裂开；
 只要吩咐，活水就流开。
 副吩咐磐石发出活水来！圣灵早已赐，早与你同在；

[V1]
 切的丰富，等着你接受；你若肯信服，必享祂富有。

[V2]
 那永久的磐石，今仍是裂开，神圣灵的恩赐，今仍在等待；
 祂仍在说，挣扎果为何？只与主死合，立刻解干渴；

[V1]
 经约旦，就必得圣鸽。

[V3]
 但愿心肯简单，完全的相信！但愿心能平安，不再苦求寻！
 如同婴孩，静卧主怀间，向世界断奶，饱尝祂爱甜，
 灵得安息，全由祂充满。+词：Albert Benjamin Simpson, 曲：(不详),
 THE END
</lyrics>
  <author></author>
  <copyright></copyright>
  <hymn_number></hymn_number>
  <presentation></presentation>
  <ccli></ccli>
  <capo print="false"></capo>
  <key></key>
  <aka></aka>
  <key_line></key_line>
  <user1></user1>
  <user2></user2>
  <user3></user3>
  <theme></theme>
  <linked_songs/>
  <tempo></tempo>
  <time_sig></time_sig>
  <backgrounds resize="screen" keep_aspect="false" link="false" background_as_text="false"/>
</song>
