<?xml version="1.0" encoding="UTF-8"?>
<song>
  <title>169 - 主活我里面</title>
  <lyrics>[V1]
 前远离神死在罪中, 
 黑暗蒙蔽心眼;
 今蒙主话照明得知, 
 主活在我里面。

[C]
 主活我里面, 
 主活我里面,
 哦,这是何等救恩, 
 主竟活我里面。

[V2]
 如同阳光照射大地, 
 百花盛开争艳; 
 生命,光,爱从主而来, 
 祂活在我里面。 

[V3]
 正如花木生命特征, 
 孕于种子里面, 
 同样,满带真理、恩典,
 主活在我里面。

[V4]
 我心不禁羡慕象祂, 
 完全将祂彰显; 
 我被吸引不断思量, 
 主活在我里面。
</lyrics>
  <author></author>
  <copyright></copyright>
  <hymn_number></hymn_number>
  <presentation></presentation>
  <ccli></ccli>
  <capo print="false"></capo>
  <key></key>
  <aka></aka>
  <key_line></key_line>
  <user1></user1>
  <user2></user2>
  <user3></user3>
  <theme></theme>
  <linked_songs/>
  <tempo></tempo>
  <time_sig></time_sig>
  <backgrounds resize="screen" keep_aspect="false" link="false" background_as_text="false"/>
</song>