<?xml version="1.0" encoding="UTF-8"?>
<song>
  <title>171 - 爱何大寻回我</title>
  <lyrics>[V1]
 当我疲困罪恶境, 
 祂以柔爱来寻, 
 怀我、肩我满温情, 
 带我归祂羊群; 
 千万天使因此欢腾, 
 甚至歌声满天响应。
[C]
 爱何大, 寻回我! 
 血何宝, 赎回我! 
 恩何丰, 带回我归羊群! 
 奇妙恩, 带回我归羊群!

[V2]
 伤重待毙祂见我, 
 便以油酒敷裹; 
 柔声细语许我说;
 “你要永远属我!” 
 从无声音如此甜美, 
 伤痛之心顿觉欣慰!
 
[V3]
 钉痕枪伤祂示我, 
 血也水也流出, 
 头戴荆冕利刺戳,
 羞辱加上痛楚:
 我真不知我有何长,
 使祂为我这样受戕。
 
[V4]
 我今安坐祂面前, 
 瞻仰祂的荣颜, 
 心觉希奇灵感赞, 
 追忆祂的恩眷; 
 似乎永世所有时间, 
 用来赞祂尚嫌太短。

[V5]
 虽然年日在逝去, 
 今享完全安息; 
 惟独切盼那早晨- 
 无上光明时辰: 
 那时召我到祂身边, 
 与祂同在,作祂圣伴。
</lyrics>
  <author></author>
  <copyright></copyright>
  <hymn_number></hymn_number>
  <presentation></presentation>
  <ccli></ccli>
  <capo print="false"></capo>
  <key></key>
  <aka></aka>
  <key_line></key_line>
  <user1></user1>
  <user2></user2>
  <user3></user3>
  <theme></theme>
  <linked_songs/>
  <tempo></tempo>
  <time_sig></time_sig>
  <backgrounds resize="screen" keep_aspect="false" link="false" background_as_text="false"/>
</song>