<?xml version="1.0" encoding="UTF-8"?>
<song>
  <title>349 - 哦主耶稣当你在地</title>
  <lyrics>[V1]
 哦,主耶稣,当你在地, 
 他们与你多年同处; 
 但是他们对你自己, 
 似识不识,似悟不悟。

[V2]
 他们听过你的声音, 
 他们见过你的丰姿, 
 他们挤过你的肉身, 
 但你是谁,似知不知。 

[V3]
 我们好象盖重幔子, 
 仿佛知道,又不透明, 
 说不认识,早已认识, 
 说已认识,认识不清。 

[V4]
 但你今已在灵里面, 
 成为另一位保惠师, 
 你已使我成你圣殿, 
 在我里面将你启示。 

[V5]
 但愿你用圣灵充满 
 我的全人每一角落, 
 没有一处不受你感, 
 没有一处不被你摸。 

[V6]
 求你自己借灵显现, 
 加倍实在,在我心怀; 
 无耳所听,无目所见, 
 无手所摸,如此实在。 

[V7]
 当你怜悯,肯来启示, 
 将你自己给了我们, 
 世上有谁比你更实? 
 世上有何比你更真? 

[V8]
 求你用灵从我的灵, 
 如同洪水漫溢全人: 
 到处荣耀,到处光明, 
 到处是你,到处是神。 

[V9]
 这个生活何等亲近! 
 你使我已在地若天: 
 赞美满口,喜乐满心, 
 同在满魂,一切甘甜。
</lyrics>
  <author></author>
  <copyright></copyright>
  <hymn_number></hymn_number>
  <presentation></presentation>
  <ccli></ccli>
  <capo print="false"></capo>
  <key></key>
  <aka></aka>
  <key_line></key_line>
  <user1></user1>
  <user2></user2>
  <user3></user3>
  <theme></theme>
  <linked_songs/>
  <tempo></tempo>
  <time_sig></time_sig>
  <backgrounds resize="screen" keep_aspect="false" link="false" background_as_text="false"/>
</song>