<?xml version="1.0" encoding="UTF-8"?>
<song>
  <title>D477 主耶稣，你是如此美丽</title>
  <lyrics>[v1]
 主耶稣，你是如此美丽，
 在你里喜乐又平安，使我安息。
 哦，主，将爱和亮光来赐， 
 愿多思念上面的事，越过地影遮蔽。

[c]
 主啊，救我脱离所有虚空定意，
 让我献上我的每日每夜于你；
 主，使我与你无间隔，与你亲密祥和；
 哦，主啊，每时每刻领我。

[v2]   
 若我魂远离灵中声音，
 若怀疑、惊惧欺我魂，占据我心；
 哦，主，将信更多注我里，
 盖上印记，使我知悉-宝血买我归你。


  </lyrics>
  <author></author>
  <copyright></copyright>
  <hymn_number></hymn_number>
  <presentation></presentation>
  <ccli></ccli>
  <capo print="false"></capo>
  <key></key>
  <aka></aka>
  <key_line></key_line>
  <user1></user1>
  <user2></user2>
  <user3></user3>
  <theme></theme>
  <linked_songs/>
  <tempo></tempo>
  <time_sig></time_sig>
  <backgrounds resize="screen" keep_aspect="false" link="false" background_as_text="false"/>
</song>