<?xml version="1.0" encoding="UTF-8"?>
<song>
  <title>162 - 来啊你这万福泉源</title>
  <lyrics>[V1]
 来啊,你这万福泉源! 
 调整我心来歌唱; 
 怜悯江河涌流不断, 
 召我高声来颂扬。 
 我本外人离神流浪, 
 基督亲来寻找我; 
 因要救我脱离死亡, 
 祂竟为我被钉戳。

[V2]
 我今天天被你激励,
 对你恩典来负债; 
 我主,让此恩典维系
 我这流浪的心怀。 
 我认我是趋向流浪,
 趋向离开爱的神; 
 但你竟用圣灵力量,
 将我荡心来吸引。 

[V3]
 我已得着宝血救恩,
 脱离罪恶和死亡; 
 但愿能作脱俗的人,
 显出神子的景况。 
 我今唱起“以便以谢,”
 因你一直赐帮助; 
 因你喜悦,我望永得
 你的带领和眷顾。
</lyrics>
  <author></author>
  <copyright></copyright>
  <hymn_number></hymn_number>
  <presentation></presentation>
  <ccli></ccli>
  <capo print="false"></capo>
  <key></key>
  <aka></aka>
  <key_line></key_line>
  <user1></user1>
  <user2></user2>
  <user3></user3>
  <theme></theme>
  <linked_songs/>
  <tempo></tempo>
  <time_sig></time_sig>
  <backgrounds resize="screen" keep_aspect="false" link="false" background_as_text="false"/>
</song>