<?xml version="1.0" encoding="UTF-8"?>
<song>
  <title>246 - 如鹿切慕溪水</title>
  <lyrics>[V1]
 如鹿切慕溪水的心怀, 
 哦神,我切慕要你。
 惟有你是我心所珍爱, 
 我渴慕来敬拜你。
[C]
 你是我的力量,盾牌, 
 我的灵单单降服于你。
 惟有你是我心所珍爱, 
 我渴慕来敬拜你。

[V2]
 主,你是我友,我的弟兄,
 虽然你也是君王;
 我的心爱你,为你心倾,
 胜过其它的对象。


[V3]
 宁舍金银,为将你得着,
 惟有你满足我心;
 惟有你能赐真实喜乐,
 是我眼中的瞳人。
</lyrics>
  <author></author>
  <copyright></copyright>
  <hymn_number></hymn_number>
  <presentation></presentation>
  <ccli></ccli>
  <capo print="false"></capo>
  <key></key>
  <aka></aka>
  <key_line></key_line>
  <user1></user1>
  <user2></user2>
  <user3></user3>
  <theme></theme>
  <linked_songs/>
  <tempo></tempo>
  <time_sig></time_sig>
  <backgrounds resize="screen" keep_aspect="false" link="false" background_as_text="false"/>
</song>