<?xml version="1.0" encoding="UTF-8"?>
<song>
  <title>父你爱子率领我们赞美</title>
  <lyrics>[V1] 
 筵宴方过,我们尚感甜美,
 父,你爱子率领我们赞美;
 祂领诗歌,于你何亲,何甜,
 我们与祂一致,和声颂赞。

[V2]
 哦父,你外我们不需别惠,
 有何比你恩爱更为宝贵! 
 我们敬拜,因为我们尝到
 你那无穷生命丰美味道。  

[V3]
 在你爱中我爱对你增长,
 胜过所有人情、属地捆绑;
 你爱借着大能,带领我心
 享受你的同在与日俱深。 

[V4]
 父啊,我们跟随你的爱子,
 在此向你赞美颂扬不止;
 饱享你的圣爱,心满意足,
 众子尝到你名所有丰富。
</lyrics>
  <author></author>
  <copyright></copyright>
  <hymn_number></hymn_number>
  <presentation></presentation>
  <ccli></ccli>
  <capo print="false"></capo>
  <key></key>
  <aka></aka>
  <key_line></key_line>
  <user1></user1>
  <user2></user2>
  <user3></user3>
  <theme></theme>
  <linked_songs/>
  <tempo></tempo>
  <time_sig></time_sig>
  <backgrounds resize="screen" keep_aspect="false" link="false" background_as_text="false"/>
</song>