<?xml version="1.0" encoding="UTF-8"?>
<song>
  <title>413 - 意志薄弱能力软弱</title>
  <lyrics>[V1]
 意志薄弱,能力软弱, 
 盼望都已消灭; 
 只有信托你的工作 
 将我温柔提挈。

[V2]
 尽我所有,所有失败,
 至今失败频仍; 
 无何可信,信你能耐,
 使我听你命令。 

[V3]
 当我的心稍微高仰,
 我就仆跌近地; 
 我不敢作,我不敢想,
 事事我需要你。

[V4]
 你是救主…刚强…体贴,
 你面我今求祈; 
 虽然我是弱中弱者,
 你恩仍加我力。</lyrics>
  <author></author>
  <copyright></copyright>
  <hymn_number></hymn_number>
  <presentation></presentation>
  <ccli></ccli>
  <capo print="false"></capo>
  <key></key>
  <aka></aka>
  <key_line></key_line>
  <user1></user1>
  <user2></user2>
  <user3></user3>
  <theme></theme>
  <linked_songs/>
  <tempo></tempo>
  <time_sig></time_sig>
  <backgrounds resize="screen" keep_aspect="false" link="false" background_as_text="false"/>
</song>